{
  "build": {
    "content": [
      {
        "files": [
          "**/*.md"
        ],
        "exclude": [
          "**/obj/**",
          "BotFramework-Docs/**",
          "**/includes/**",
          "README.md",
          "LICENSE",
          "LICENSE-CODE"
        ]
      }
    ],
    "resource": [
      {
        "files": [
          "**/*.png",
          "**/*.jpg"
        ],
        "exclude": [
          "**/obj/**",
          "BotFramework-Docs/**",
          "**/includes/**"
        ]
      }
    ],
    "overwrite": [],
    "externalReference": [],
    "globalMetadata": {
      "author": "RobStand"
    },
    "fileMetadata": {
      "ms.date":
       {
         "articles/**": "03/01/2017"
       },
       "manager":
       {
         "articles/**": "rstand"
       }
    },
    "template": [],
    "dest": "BotFramework-Docs"
  }
}
